spark_dataframe_tools/__init__.py
spark_dataframe_tools/functions/__init__.py
spark_dataframe_tools/functions/generator.py
spark_dataframe_tools/utils/__init__.py
spark_dataframe_tools/utils/utils_color.py
spark_dataframe_tools/utils/utils_enviroment.py
spark_dataframe_tools/utils/utils_faker.py
spark_dataframe_tools/utils/utils_reformat_type.py
spark_dataframe_tools/utils/utils_session_retry.py
spark_dataframe_tools/utils/utils_size.py
spark_dataframe_tools/utils/templates/__init__.py
spark_dataframe_tools/utils/templates/table.html
tests/__init__.py
spark_dataframe_tools-0.7.2.dist-info/LICENSE
spark_dataframe_tools-0.7.2.dist-info/METADATA
spark_dataframe_tools-0.7.2.dist-info/WHEEL
spark_dataframe_tools-0.7.2.dist-info/top_level.txt
spark_dataframe_tools-0.7.2.dist-info/RECORD
