Metadata-Version: 2.1
Name: spark-dataframe-tools
Version: 0.7.2
Summary: spark_dataframe_tools
Home-page: https://github.com/jonaqp/spark_dataframe_tools/
Author: Jonathan Quiza
Author-email: jony327@gmail.com
License: UNKNOWN
Download-URL: https://github.com/jonaqp/spark_dataframe_tools/archive/main.zip
Keywords: spark,dataframe
Platform: UNKNOWN
Classifier: Development Status :: 5 - Production/Stable
Classifier: Intended Audience :: Developers
Classifier: Intended Audience :: Science/Research
Classifier: Topic :: Scientific/Engineering :: Artificial Intelligence
Classifier: License :: OSI Approved :: Apache Software License
Classifier: Programming Language :: Python :: 3.9
License-File: LICENSE
Requires-Dist: pandas (>=1.5.3)
Requires-Dist: numpy (>=1.24.3)
Requires-Dist: findspark (==2.0.1)
Requires-Dist: pyspark (==3.1.1)
Requires-Dist: pyarrow (>=12.0.1)
Requires-Dist: setuptools (>=58.2.0)
Requires-Dist: jinja2 (>=3.1.4)
Requires-Dist: humanize (>=4.10.0)
Requires-Dist: wheel (>=0.40.0)
Requires-Dist: color-tools (>=0.0.2)
Requires-Dist: faker (>=26.1.0)
Requires-Dist: prettytable (>=3.12.0)
Requires-Dist: pyhocon (>=0.3.61)
Requires-Dist: ipython
